{"id": "IZBlqcbpmxY", "title": "Jimi Hendrix - Voodoo Child (Slight Return)", "formats": [{"asr": 48000, "filesize": 1899568, "format_id": "249", "format_note": "tiny", "fps": null, "height": null, "quality": 0, "tbr": 48.467, "url": "https://rr4---sn-0opoxu-ihv6.googlevideo.com/videoplayback?expire=1670697785&ei=2X6UY7OeEI30kgbHo7z4Cw&ip=189.173.225.87&id=o-AOAj3b2OrNWhfJszppld8ApRwwiZ8ydqEkMy76gwdpEb&itag=249&source=youtube&requiressl=yes&mh=6I&mm=31%2C29&mn=sn-0opoxu-ihv6%2Csn-q4flrn7r&ms=au%2Crdu&mv=m&mvi=4&pl=24&initcwndbps=1000000&vprv=1&mime=audio%2Fwebm&ns=NTU2HOwc2ZEoFEnMJwttG7YJ&gir=yes&clen=1899568&dur=313.541&lmt=1552098223208551&mt=1670675841&fvip=1&keepalive=yes&fexp=24001373%2C24007246&c=WEB&txp=5511222&n=8-ijwIPTxiU27OGOS&sparams=expire%2Cei%2Cip%2Cid%2Citag%2Csource%2Crequiressl%2Cvprv%2Cmime%2Cns%2Cgir%2Cclen%2Cdur%2Clmt&lsparams=mh%2Cmm%2Cmn%2Cms%2Cmv%2Cmvi%2Cpl%2Cinitcwndbps&lsig=AG3C_xAwRQIgBtkuMq8xktMLmll4GqFf4JQlOjd6YkvLg-f67v9zwOYCIQDqm9ZWuTa4O6s2JjA63ew-BpT-6bT4FDLLtvZzGZAZUg%3D%3D&sig=AOq0QJ8wRQIgMMSMRp6n-UQVOQBo0m8gwOle0B8Ga8XCkhO-Jb3zwRgCIQDgsK4BRAd7fOAQIpxw7_0wZSEyMH-SYxF0SBUd5SAvug==", "width": null, "ext": "webm", "vcodec": "none", "acodec": "opus", "abr": 48.467, "downloader_options": {"http_chunk_size": 10485760}, "container": "webm_dash", "format": "249 - audio only (tiny)", "protocol": "https", "http_headers": {"User-Agent": "Mozilla/5.0 (Windows NT 10.0; Win64; x64) AppleWebKit/537.36 (KHTML, like Gecko) Chrome/72.0.3592.0 Safari/537.36", "Accept-Charset": "ISO-8859-1,utf-8;q=0.7,*;q=0.7", "Accept": "text/html,application/xhtml+xml,application/xml;q=0.9,*/*;q=0.8", "Accept-Encoding": "gzip, deflate", "Accept-Language": "en-us,en;q=0.5"}}, {"asr": 48000, "filesize": 2516920, "format_id": "250", "format_note": "tiny", "fps": null, "height": null, "quality": 0, "tbr": 64.219, "url": "https://rr4---sn-0opoxu-ihv6.googlevideo.com/videoplayback?expire=1670697785&ei=2X6UY7OeEI30kgbHo7z4Cw&ip=189.173.225.87&id=o-AOAj3b2OrNWhfJszppld8ApRwwiZ8ydqEkMy76gwdpEb&itag=250&source=youtube&requiressl=yes&mh=6I&mm=31%2C29&mn=sn-0opoxu-ihv6%2Csn-q4flrn7r&ms=au%2Crdu&mv=m&mvi=4&pl=24&initcwndbps=1000000&vprv=1&mime=audio%2Fwebm&ns=NTU2HOwc2ZEoFEnMJwttG7YJ&gir=yes&clen=2516920&dur=313.541&lmt=1552098229764866&mt=1670675841&fvip=1&keepalive=yes&fexp=24001373%2C24007246&c=WEB&txp=5511222&n=8-ijwIPTxiU27OGOS&sparams=expire%2Cei%2Cip%2Cid%2Citag%2Csource%2Crequiressl%2Cvprv%2Cmime%2Cns%2Cgir%2Cclen%2Cdur%2Clmt&lsparams=mh%2Cmm%2Cmn%2Cms%2Cmv%2Cmvi%2Cpl%2Cinitcwndbps&lsig=AG3C_xAwRgIhAJ1qfBwNhnD0cNONycgW7mZIfDLoO_aEuDR8S3Zsqc1AAiEAl7gbptHHv_k0tK88LnSN4YoCuNu9DxDtyv6LaaYPlw8%3D&sig=AOq0QJ8wRQIgNOCsHS8a9T1sa40FWUtCvLPINy1iVV4k5E5VOOJ3jOMCIQDAdZsTePft1z9nK6LODoR_6Vs2gwL65R9CTr2Vyhk5rw==", "width": null, "ext": "webm", "vcodec": "none", "acodec": "opus", "abr": 64.219, "downloader_options": {"http_chunk_size": 10485760}, "container": "webm_dash", "format": "250 - audio only (tiny)", "protocol": "https", "http_headers": {"User-Agent": "Mozilla/5.0 (Windows NT 10.0; Win64; x64) AppleWebKit/537.36 (KHTML, like Gecko) Chrome/72.0.3592.0 Safari/537.36", "Accept-Charset": "ISO-8859-1,utf-8;q=0.7,*;q=0.7", "Accept": "text/html,application/xhtml+xml,application/xml;q=0.9,*/*;q=0.8", "Accept-Encoding": "gzip, deflate", "Accept-Language": "en-us,en;q=0.5"}}, {"asr": 48000, "filesize": 5033558, "format_id": "251", "format_note": "tiny", "fps": null, "height": null, "quality": 0, "tbr": 128.431, "url": "https://rr4---sn-0opoxu-ihv6.googlevideo.com/videoplayback?expire=1670697785&ei=2X6UY7OeEI30kgbHo7z4Cw&ip=189.173.225.87&id=o-AOAj3b2OrNWhfJszppld8ApRwwiZ8ydqEkMy76gwdpEb&itag=251&source=youtube&requiressl=yes&mh=6I&mm=31%2C29&mn=sn-0opoxu-ihv6%2Csn-q4flrn7r&ms=au%2Crdu&mv=m&mvi=4&pl=24&initcwndbps=1000000&vprv=1&mime=audio%2Fwebm&ns=NTU2HOwc2ZEoFEnMJwttG7YJ&gir=yes&clen=5033558&dur=313.541&lmt=1552098221844929&mt=1670675841&fvip=1&keepalive=yes&fexp=24001373%2C24007246&c=WEB&txp=5511222&n=8-ijwIPTxiU27OGOS&sparams=expire%2Cei%2Cip%2Cid%2Citag%2Csource%2Crequiressl%2Cvprv%2Cmime%2Cns%2Cgir%2Cclen%2Cdur%2Clmt&lsparams=mh%2Cmm%2Cmn%2Cms%2Cmv%2Cmvi%2Cpl%2Cinitcwndbps&lsig=AG3C_xAwRQIgbdmkZXOu-g9zIO7xW6FVX9cpk52lBcqyxSOKUVXfM_UCIQC1BO9qYs8gtB7WQjAQN6Ph-S9Q44wa_-VBITWcdeBTdw%3D%3D&sig=AOq0QJ8wRQIgVr2O6DWPY6epTlIRVICxcW_uL-8GCwpxI6P7riGnzX4CIQCc-b0a5Sadj3-H3_2vgdtwtCi3Loco8jSWimU-RpaGYA==", "width": null, "ext": "webm", "vcodec": "none", "acodec": "opus", "abr": 128.431, "downloader_options": {"http_chunk_size": 10485760}, "container": "webm_dash", "format": "251 - audio only (tiny)", "protocol": "https", "http_headers": {"User-Agent": "Mozilla/5.0 (Windows NT 10.0; Win64; x64) AppleWebKit/537.36 (KHTML, like Gecko) Chrome/72.0.3592.0 Safari/537.36", "Accept-Charset": "ISO-8859-1,utf-8;q=0.7,*;q=0.7", "Accept": "text/html,application/xhtml+xml,application/xml;q=0.9,*/*;q=0.8", "Accept-Encoding": "gzip, deflate", "Accept-Language": "en-us,en;q=0.5"}}, {"asr": 44100, "filesize": 5075412, "format_id": "140", "format_note": "tiny", "fps": null, "height": null, "quality": 0, "tbr": 129.49, "url": "https://rr4---sn-0opoxu-ihv6.googlevideo.com/videoplayback?expire=1670697785&ei=2X6UY7OeEI30kgbHo7z4Cw&ip=189.173.225.87&id=o-AOAj3b2OrNWhfJszppld8ApRwwiZ8ydqEkMy76gwdpEb&itag=140&source=youtube&requiressl=yes&mh=6I&mm=31%2C29&mn=sn-0opoxu-ihv6%2Csn-q4flrn7r&ms=au%2Crdu&mv=m&mvi=4&pl=24&initcwndbps=1000000&vprv=1&mime=audio%2Fmp4&ns=NTU2HOwc2ZEoFEnMJwttG7YJ&gir=yes&clen=5075412&dur=313.562&lmt=1556962071769610&mt=1670675841&fvip=1&keepalive=yes&fexp=24001373%2C24007246&c=WEB&txp=5535432&n=8-ijwIPTxiU27OGOS&sparams=expire%2Cei%2Cip%2Cid%2Citag%2Csource%2Crequiressl%2Cvprv%2Cmime%2Cns%2Cgir%2Cclen%2Cdur%2Clmt&lsparams=mh%2Cmm%2Cmn%2Cms%2Cmv%2Cmvi%2Cpl%2Cinitcwndbps&lsig=AG3C_xAwRQIhAIwCXbgUS94PqIcQ08nFs73o8i3IwSmiOhpYM3Hjqu9aAiB6eGGXTUuVEb-dyfq_iqSB0yUR0znkhcaQ5V-xPWwTCA%3D%3D&sig=AOq0QJ8wRQIhAPZRbMJ7gmn5NvpuRRXXsgf3D9kfe32ruVawLrxPxmS7AiBgqYo1ILppU2c9zjL4PUbOiIhD_z4eOISmwfK2pYk7oQ==", "width": null, "ext": "m4a", "vcodec": "none", "acodec": "mp4a.40.2", "abr": 129.49, "downloader_options": {"http_chunk_size": 10485760}, "container": "m4a_dash", "format": "140 - audio only (tiny)", "protocol": "https", "http_headers": {"User-Agent": "Mozilla/5.0 (Windows NT 10.0; Win64; x64) AppleWebKit/537.36 (KHTML, like Gecko) Chrome/72.0.3592.0 Safari/537.36", "Accept-Charset": "ISO-8859-1,utf-8;q=0.7,*;q=0.7", "Accept": "text/html,application/xhtml+xml,application/xml;q=0.9,*/*;q=0.8", "Accept-Encoding": "gzip, deflate", "Accept-Language": "en-us,en;q=0.5"}}, {"asr": null, "filesize": 1685709, "format_id": "160", "format_note": "144p", "fps": 30, "height": 144, "quality": 0, "tbr": 43.014, "url": "https://rr4---sn-0opoxu-ihv6.googlevideo.com/videoplayback?expire=1670697785&ei=2X6UY7OeEI30kgbHo7z4Cw&ip=189.173.225.87&id=o-AOAj3b2OrNWhfJszppld8ApRwwiZ8ydqEkMy76gwdpEb&itag=160&aitags=133%2C134%2C135%2C136%2C137%2C160%2C242%2C243%2C244%2C247%2C248%2C278%2C394%2C395%2C396%2C397%2C398%2C399&source=youtube&requiressl=yes&mh=6I&mm=31%2C29&mn=sn-0opoxu-ihv6%2Csn-q4flrn7r&ms=au%2Crdu&mv=m&mvi=4&pl=24&initcwndbps=1000000&vprv=1&mime=video%2Fmp4&ns=NTU2HOwc2ZEoFEnMJwttG7YJ&gir=yes&clen=1685709&dur=313.513&lmt=1556962778364896&mt=1670675841&fvip=1&keepalive=yes&fexp=24001373%2C24007246&c=WEB&txp=5535432&n=8-ijwIPTxiU27OGOS&sparams=expire%2Cei%2Cip%2Cid%2Caitags%2Csource%2Crequiressl%2Cvprv%2Cmime%2Cns%2Cgir%2Cclen%2Cdur%2Clmt&lsparams=mh%2Cmm%2Cmn%2Cms%2Cmv%2Cmvi%2Cpl%2Cinitcwndbps&lsig=AG3C_xAwRQIhANlzbPMXk6iDL30rsDwrzFpQA9axp4Ob-fTMFzxShm2aAiBz2KLqbzQ_UQ0cADPoTqMhL5uYjBN5BYnS9UvQThmtYg%3D%3D&sig=AOq0QJ8wRAIgGfVFi0NX2L4SdtZfN-8R-YCWdlSPaOZIMHWyE8Uz1NUCIFiMbR7GRh_p3stebWyCAvw31T2vjR60YScyZ_jgCZya", "width": 192, "ext": "mp4", "vcodec": "avc1.4d400c", "acodec": "none", "vbr": 43.014, "downloader_options": {"http_chunk_size": 10485760}, "container": "mp4_dash", "format": "160 - 192x144 (144p)", "protocol": "https", "http_headers": {"User-Agent": "Mozilla/5.0 (Windows NT 10.0; Win64; x64) AppleWebKit/537.36 (KHTML, like Gecko) Chrome/72.0.3592.0 Safari/537.36", "Accept-Charset": "ISO-8859-1,utf-8;q=0.7,*;q=0.7", "Accept": "text/html,application/xhtml+xml,application/xml;q=0.9,*/*;q=0.8", "Accept-Encoding": "gzip, deflate", "Accept-Language": "en-us,en;q=0.5"}}, {"asr": null, "filesize": 2037329, "format_id": "394", "format_note": "144p", "fps": 30, "height": 144, "quality": 0, "tbr": 51.987, "url": "https://rr4---sn-0opoxu-ihv6.googlevideo.com/videoplayback?expire=1670697785&ei=2X6UY7OeEI30kgbHo7z4Cw&ip=189.173.225.87&id=o-AOAj3b2OrNWhfJszppld8ApRwwiZ8ydqEkMy76gwdpEb&itag=394&aitags=133%2C134%2C135%2C136%2C137%2C160%2C242%2C243%2C244%2C247%2C248%2C278%2C394%2C395%2C396%2C397%2C398%2C399&source=youtube&requiressl=yes&mh=6I&mm=31%2C29&mn=sn-0opoxu-ihv6%2Csn-q4flrn7r&ms=au%2Crdu&mv=m&mvi=4&pl=24&initcwndbps=1000000&vprv=1&mime=video%2Fmp4&ns=NTU2HOwc2ZEoFEnMJwttG7YJ&gir=yes&clen=2037329&dur=313.513&lmt=1668715188174836&mt=1670675841&fvip=1&keepalive=yes&fexp=24001373%2C24007246&c=WEB&txp=5537434&n=8-ijwIPTxiU27OGOS&sparams=expire%2Cei%2Cip%2Cid%2Caitags%2Csource%2Crequiressl%2Cvprv%2Cmime%2Cns%2Cgir%2Cclen%2Cdur%2Clmt&lsparams=mh%2Cmm%2Cmn%2Cms%2Cmv%2Cmvi%2Cpl%2Cinitcwndbps&lsig=AG3C_xAwRQIgYyM_hPAT5h668LyOSR5blFqTULOX-uMbF9RQyVE0n6kCIQCXu3TIjU373jSfdIfSx3VaUarFwtsaKNy9U3FXwh3V_Q%3D%3D&sig=AOq0QJ8wRQIgUZr9fTMh9w_2u4-WdQsTxE3AYeqfrfV9mv-8_ERXlroCIQD03YGBOOT0wOaN1fNzvklLjpPNBLKV-hyuCRnlMQSk_w==", "width": 192, "ext": "mp4", "vcodec": "av01.0.00M.08", "acodec": "none", "vbr": 51.987, "downloader_options": {"http_chunk_size": 10485760}, "container": "mp4_dash", "format": "394 - 192x144 (144p)", "protocol": "https", "http_headers": {"User-Agent": "Mozilla/5.0 (Windows NT 10.0; Win64; x64) AppleWebKit/537.36 (KHTML, like Gecko) Chrome/72.0.3592.0 Safari/537.36", "Accept-Charset": "ISO-8859-1,utf-8;q=0.7,*;q=0.7", "Accept": "text/html,application/xhtml+xml,application/xml;q=0.9,*/*;q=0.8", "Accept-Encoding": "gzip, deflate", "Accept-Language": "en-us,en;q=0.5"}}, {"asr": null, "filesize": 2853622, "format_id": "278", "format_note": "144p", "fps": 30, "height": 144, "quality": 0, "tbr": 72.816, "url": "https://rr4---sn-0opoxu-ihv6.googlevideo.com/videoplayback?expire=1670697785&ei=2X6UY7OeEI30kgbHo7z4Cw&ip=189.173.225.87&id=o-AOAj3b2OrNWhfJszppld8ApRwwiZ8ydqEkMy76gwdpEb&itag=278&aitags=133%2C134%2C135%2C136%2C137%2C160%2C242%2C243%2C244%2C247%2C248%2C278%2C394%2C395%2C396%2C397%2C398%2C399&source=youtube&requiressl=yes&mh=6I&mm=31%2C29&mn=sn-0opoxu-ihv6%2Csn-q4flrn7r&ms=au%2Crdu&mv=m&mvi=4&pl=24&initcwndbps=1000000&vprv=1&mime=video%2Fwebm&ns=NTU2HOwc2ZEoFEnMJwttG7YJ&gir=yes&clen=2853622&dur=313.513&lmt=1667584594754775&mt=1670675841&fvip=1&keepalive=yes&fexp=24001373%2C24007246&c=WEB&txp=5535434&n=8-ijwIPTxiU27OGOS&sparams=expire%2Cei%2Cip%2Cid%2Caitags%2Csource%2Crequiressl%2Cvprv%2Cmime%2Cns%2Cgir%2Cclen%2Cdur%2Clmt&lsparams=mh%2Cmm%2Cmn%2Cms%2Cmv%2Cmvi%2Cpl%2Cinitcwndbps&lsig=AG3C_xAwRQIgP8rvX_camzHZBXLX0MkIJZkC1dgBWBuMRFluTurd82ICIQC1F04un4DGXFVCcUwywUT8j3xkXms21uyTlZnp5pP6Sw%3D%3D&sig=AOq0QJ8wRQIhAMo2AFnkJHfYBO-cW4wPlfjPGCGy76tP61wDI2ITi2wPAiAXWNW7EOP029YrvbBhNxc6X5qks-rYPmWB1PXapiY6wQ==", "width": 192, "ext": "webm", "vcodec": "vp9", "acodec": "none", "vbr": 72.816, "downloader_options": {"http_chunk_size": 10485760}, "container": "webm_dash", "format": "278 - 192x144 (144p)", "protocol": "https", "http_headers": {"User-Agent": "Mozilla/5.0 (Windows NT 10.0; Win64; x64) AppleWebKit/537.36 (KHTML, like Gecko) Chrome/72.0.3592.0 Safari/537.36", "Accept-Charset": "ISO-8859-1,utf-8;q=0.7,*;q=0.7", "Accept": "text/html,application/xhtml+xml,application/xml;q=0.9,*/*;q=0.8", "Accept-Encoding": "gzip, deflate", "Accept-Language": "en-us,en;q=0.5"}}, {"asr": null, "filesize": 2756609, "format_id": "395", "format_note": "240p", "fps": 30, "height": 240, "quality": 1, "tbr": 70.341, "url": "https://rr4---sn-0opoxu-ihv6.googlevideo.com/videoplayback?expire=1670697785&ei=2X6UY7OeEI30kgbHo7z4Cw&ip=189.173.225.87&id=o-AOAj3b2OrNWhfJszppld8ApRwwiZ8ydqEkMy76gwdpEb&itag=395&aitags=133%2C134%2C135%2C136%2C137%2C160%2C242%2C243%2C244%2C247%2C248%2C278%2C394%2C395%2C396%2C397%2C398%2C399&source=youtube&requiressl=yes&mh=6I&mm=31%2C29&mn=sn-0opoxu-ihv6%2Csn-q4flrn7r&ms=au%2Crdu&mv=m&mvi=4&pl=24&initcwndbps=1000000&vprv=1&mime=video%2Fmp4&ns=NTU2HOwc2ZEoFEnMJwttG7YJ&gir=yes&clen=2756609&dur=313.513&lmt=1668715201612855&mt=1670675841&fvip=1&keepalive=yes&fexp=24001373%2C24007246&c=WEB&txp=5537434&n=8-ijwIPTxiU27OGOS&sparams=expire%2Cei%2Cip%2Cid%2Caitags%2Csource%2Crequiressl%2Cvprv%2Cmime%2Cns%2Cgir%2Cclen%2Cdur%2Clmt&lsparams=mh%2Cmm%2Cmn%2Cms%2Cmv%2Cmvi%2Cpl%2Cinitcwndbps&lsig=AG3C_xAwRQIhAOE9bAGMYf1VPkfu_ZgVMPAU2tr5XyPeArH1VEpg-Ts3AiB06aJJbgL33dQqcLCWn32mm4yjkBAEh_pWI_TFryFWdg%3D%3D&sig=AOq0QJ8wRgIhANUnVfpOGKntAEqGdHbpMAvnveBJozZYZbhPj0Av7GrZAiEAyMpsk-uVuLw26MtqcJKRaL_jz8vCbuka_qeqJD9ylpM=", "width": 320, "ext": "mp4", "vcodec": "av01.0.00M.08", "acodec": "none", "vbr": 70.341, "downloader_options": {"http_chunk_size": 10485760}, "container": "mp4_dash", "format": "395 - 320x240 (240p)", "protocol": "https", "http_headers": {"User-Agent": "Mozilla/5.0 (Windows NT 10.0; Win64; x64) AppleWebKit/537.36 (KHTML, like Gecko) Chrome/72.0.3592.0 Safari/537.36", "Accept-Charset": "ISO-8859-1,utf-8;q=0.7,*;q=0.7", "Accept": "text/html,application/xhtml+xml,application/xml;q=0.9,*/*;q=0.8", "Accept-Encoding": "gzip, deflate", "Accept-Language": "en-us,en;q=0.5"}}, {"asr": null, "filesize": 3368274, "format_id": "242", "format_note": "240p", "fps": 30, "height": 240, "quality": 1, "tbr": 85.949, "url": "https://rr4---sn-0opoxu-ihv6.googlevideo.com/videoplayback?expire=1670697785&ei=2X6UY7OeEI30kgbHo7z4Cw&ip=189.173.225.87&id=o-AOAj3b2OrNWhfJszppld8ApRwwiZ8ydqEkMy76gwdpEb&itag=242&aitags=133%2C134%2C135%2C136%2C137%2C160%2C242%2C243%2C244%2C247%2C248%2C278%2C394%2C395%2C396%2C397%2C398%2C399&source=youtube&requiressl=yes&mh=6I&mm=31%2C29&mn=sn-0opoxu-ihv6%2Csn-q4flrn7r&ms=au%2Crdu&mv=m&mvi=4&pl=24&initcwndbps=1000000&vprv=1&mime=video%2Fwebm&ns=NTU2HOwc2ZEoFEnMJwttG7YJ&gir=yes&clen=3368274&dur=313.513&lmt=1667584536512747&mt=1670675841&fvip=1&keepalive=yes&fexp=24001373%2C24007246&c=WEB&txp=5535434&n=8-ijwIPTxiU27OGOS&sparams=expire%2Cei%2Cip%2Cid%2Caitags%2Csource%2Crequiressl%2Cvprv%2Cmime%2Cns%2Cgir%2Cclen%2Cdur%2Clmt&lsparams=mh%2Cmm%2Cmn%2Cms%2Cmv%2Cmvi%2Cpl%2Cinitcwndbps&lsig=AG3C_xAwRAIgROxk0iYHFxX1-mGP6WK4Fk6dp3qgEjNFBb0jZPAd-2sCIGyHSX_i6oHiUVF8edxV7voW8zIu2N3fiaDNIwmBElvl&sig=AOq0QJ8wRQIgQ1z0rHqM8tXcYKf9w41lkVFrVEudoNE1_qSppjneOD8CIQCYfQjhTZ9cRAdXcTEFdaTZdAoVBQR251_Chxh7qTtERA==", "width": 320, "ext": "webm", "vcodec": "vp9", "acodec": "none", "vbr": 85.949, "downloader_options": {"http_chunk_size": 10485760}, "container": "webm_dash", "format": "242 - 320x240 (240p)", "protocol": "https", "http_headers": {"User-Agent": "Mozilla/5.0 (Windows NT 10.0; Win64; x64) AppleWebKit/537.36 (KHTML, like Gecko) Chrome/72.0.3592.0 Safari/537.36", "Accept-Charset": "ISO-8859-1,utf-8;q=0.7,*;q=0.7", "Accept": "text/html,application/xhtml+xml,application/xml;q=0.9,*/*;q=0.8", "Accept-Encoding": "gzip, deflate", "Accept-Language": "en-us,en;q=0.5"}}, {"asr": null, "filesize": 3528501, "format_id": "133", "format_note": "240p", "fps": 30, "height": 240, "quality": 1, "tbr": 90.037, "url": "https://rr4---sn-0opoxu-ihv6.googlevideo.com/videoplayback?expire=1670697785&ei=2X6UY7OeEI30kgbHo7z4Cw&ip=189.173.225.87&id=o-AOAj3b2OrNWhfJszppld8ApRwwiZ8ydqEkMy76gwdpEb&itag=133&aitags=133%2C134%2C135%2C136%2C137%2C160%2C242%2C243%2C244%2C247%2C248%2C278%2C394%2C395%2C396%2C397%2C398%2C399&source=youtube&requiressl=yes&mh=6I&mm=31%2C29&mn=sn-0opoxu-ihv6%2Csn-q4flrn7r&ms=au%2Crdu&mv=m&mvi=4&pl=24&initcwndbps=1000000&vprv=1&mime=video%2Fmp4&ns=NTU2HOwc2ZEoFEnMJwttG7YJ&gir=yes&clen=3528501&dur=313.513&lmt=1556962921898726&mt=1670675841&fvip=1&keepalive=yes&fexp=24001373%2C24007246&c=WEB&txp=5535432&n=8-ijwIPTxiU27OGOS&sparams=expire%2Cei%2Cip%2Cid%2Caitags%2Csource%2Crequiressl%2Cvprv%2Cmime%2Cns%2Cgir%2Cclen%2Cdur%2Clmt&lsparams=mh%2Cmm%2Cmn%2Cms%2Cmv%2Cmvi%2Cpl%2Cinitcwndbps&lsig=AG3C_xAwRAIgZHTtlXN-mfZtSyAi7lQDboU2l7B57Mc1CeocFP5hXGsCIEfhMMVyu17M7-BsfOtzabM_eB9NCHSDNbblQNqfAUd4&sig=AOq0QJ8wRQIhAJvGeav_ro4uq_peal5imgjfHot4rhLJXaRIV0perXwwAiBoknL-_9WbEBmG8KP5vf-lE_Tw2jcIKBDU3U8y6UIKNw==", "width": 320, "ext": "mp4", "vcodec": "avc1.4d400d", "acodec": "none", "vbr": 90.037, "downloader_options": {"http_chunk_size": 10485760}, "container": "mp4_dash", "format": "133 - 320x240 (240p)", "protocol": "https", "http_headers": {"User-Agent": "Mozilla/5.0 (Windows NT 10.0; Win64; x64) AppleWebKit/537.36 (KHTML, like Gecko) Chrome/72.0.3592.0 Safari/537.36", "Accept-Charset": "ISO-8859-1,utf-8;q=0.7,*;q=0.7", "Accept": "text/html,application/xhtml+xml,application/xml;q=0.9,*/*;q=0.8", "Accept-Encoding": "gzip, deflate", "Accept-Language": "en-us,en;q=0.5"}}, {"asr": null, "filesize": 5458161, "format_id": "396", "format_note": "360p", "fps": 30, "height": 360, "quality": 2, "tbr": 139.277, "url": "https://rr4---sn-0opoxu-ihv6.googlevideo.com/videoplayback?expire=1670697785&ei=2X6UY7OeEI30kgbHo7z4Cw&ip=189.173.225.87&id=o-AOAj3b2OrNWhfJszppld8ApRwwiZ8ydqEkMy76gwdpEb&itag=396&aitags=133%2C134%2C135%2C136%2C137%2C160%2C242%2C243%2C244%2C247%2C248%2C278%2C394%2C395%2C396%2C397%2C398%2C399&source=youtube&requiressl=yes&mh=6I&mm=31%2C29&mn=sn-0opoxu-ihv6%2Csn-q4flrn7r&ms=au%2Crdu&mv=m&mvi=4&pl=24&initcwndbps=1000000&vprv=1&mime=video%2Fmp4&ns=NTU2HOwc2ZEoFEnMJwttG7YJ&gir=yes&clen=5458161&dur=313.513&lmt=1668716771973736&mt=1670675841&fvip=1&keepalive=yes&fexp=24001373%2C24007246&c=WEB&txp=5537434&n=8-ijwIPTxiU27OGOS&sparams=expire%2Cei%2Cip%2Cid%2Caitags%2Csource%2Crequiressl%2Cvprv%2Cmime%2Cns%2Cgir%2Cclen%2Cdur%2Clmt&lsparams=mh%2Cmm%2Cmn%2Cms%2Cmv%2Cmvi%2Cpl%2Cinitcwndbps&lsig=AG3C_xAwRQIhAIadXON4cuMPEZqzXkGh0ItRkvyML9K9kuOyZki2eEWBAiBRh7_I0Aik7z_Zn_KoAO9FNaaMKyZGkRPwlyfq9353-A%3D%3D&sig=AOq0QJ8wRAIgKMwG4rWbDSUmORZQx_Y5c_cx_1XnN9v0x5w_ngk4Mv4CIA8AI9O6lx7bwqRKh3DwTp5UBsKcBpqJfVMEcyY1hdhK", "width": 480, "ext": "mp4", "vcodec": "av01.0.01M.08", "acodec": "none", "vbr": 139.277, "downloader_options": {"http_chunk_size": 10485760}, "container": "mp4_dash", "format": "396 - 480x360 (360p)", "protocol": "https", "http_headers": {"User-Agent": "Mozilla/5.0 (Windows NT 10.0; Win64; x64) AppleWebKit/537.36 (KHTML, like Gecko) Chrome/72.0.3592.0 Safari/537.36", "Accept-Charset": "ISO-8859-1,utf-8;q=0.7,*;q=0.7", "Accept": "text/html,application/xhtml+xml,application/xml;q=0.9,*/*;q=0.8", "Accept-Encoding": "gzip, deflate", "Accept-Language": "en-us,en;q=0.5"}}, {"asr": null, "filesize": 5586995, "format_id": "243", "format_note": "360p", "fps": 30, "height": 360, "quality": 2, "tbr": 142.564, "url": "https://rr4---sn-0opoxu-ihv6.googlevideo.com/videoplayback?expire=1670697785&ei=2X6UY7OeEI30kgbHo7z4Cw&ip=189.173.225.87&id=o-AOAj3b2OrNWhfJszppld8ApRwwiZ8ydqEkMy76gwdpEb&itag=243&aitags=133%2C134%2C135%2C136%2C137%2C160%2C242%2C243%2C244%2C247%2C248%2C278%2C394%2C395%2C396%2C397%2C398%2C399&source=youtube&requiressl=yes&mh=6I&mm=31%2C29&mn=sn-0opoxu-ihv6%2Csn-q4flrn7r&ms=au%2Crdu&mv=m&mvi=4&pl=24&initcwndbps=1000000&vprv=1&mime=video%2Fwebm&ns=NTU2HOwc2ZEoFEnMJwttG7YJ&gir=yes&clen=5586995&dur=313.513&lmt=1667584581339262&mt=1670675841&fvip=1&keepalive=yes&fexp=24001373%2C24007246&c=WEB&txp=5535434&n=8-ijwIPTxiU27OGOS&sparams=expire%2Cei%2Cip%2Cid%2Caitags%2Csource%2Crequiressl%2Cvprv%2Cmime%2Cns%2Cgir%2Cclen%2Cdur%2Clmt&lsparams=mh%2Cmm%2Cmn%2Cms%2Cmv%2Cmvi%2Cpl%2Cinitcwndbps&lsig=AG3C_xAwRgIhAKag8-eQTc_pIfW09vNNeWGnCqpVyfj2bAcG59kpKLCfAiEA_Y5dfvy5F80zRzE6LB0eu0J7eqXzQqM-x4G44rYJVRI%3D&sig=AOq0QJ8wRgIhAKAVWLYr5AclLt-DSA3oknA0fkP7ovdWte5E7jOCq8YCAiEA3q_xjzzyA_3SmdZomS1WMkoNEvBhhJ8WD4qWdPyKv58=", "width": 480, "ext": "webm", "vcodec": "vp9", "acodec": "none", "vbr": 142.564, "downloader_options": {"http_chunk_size": 10485760}, "container": "webm_dash", "format": "243 - 480x360 (360p)", "protocol": "https", "http_headers": {"User-Agent": "Mozilla/5.0 (Windows NT 10.0; Win64; x64) AppleWebKit/537.36 (KHTML, like Gecko) Chrome/72.0.3592.0 Safari/537.36", "Accept-Charset": "ISO-8859-1,utf-8;q=0.7,*;q=0.7", "Accept": "text/html,application/xhtml+xml,application/xml;q=0.9,*/*;q=0.8", "Accept-Encoding": "gzip, deflate", "Accept-Language": "en-us,en;q=0.5"}}, {"asr": null, "filesize": 6259837, "format_id": "134", "format_note": "360p", "fps": 30, "height": 360, "quality": 2, "tbr": 159.734, "url": "https://rr4---sn-0opoxu-ihv6.googlevideo.com/videoplayback?expire=1670697785&ei=2X6UY7OeEI30kgbHo7z4Cw&ip=189.173.225.87&id=o-AOAj3b2OrNWhfJszppld8ApRwwiZ8ydqEkMy76gwdpEb&itag=134&aitags=133%2C134%2C135%2C136%2C137%2C160%2C242%2C243%2C244%2C247%2C248%2C278%2C394%2C395%2C396%2C397%2C398%2C399&source=youtube&requiressl=yes&mh=6I&mm=31%2C29&mn=sn-0opoxu-ihv6%2Csn-q4flrn7r&ms=au%2Crdu&mv=m&mvi=4&pl=24&initcwndbps=1000000&vprv=1&mime=video%2Fmp4&ns=NTU2HOwc2ZEoFEnMJwttG7YJ&gir=yes&clen=6259837&dur=313.513&lmt=1556962973739906&mt=1670675841&fvip=1&keepalive=yes&fexp=24001373%2C24007246&c=WEB&txp=5535432&n=8-ijwIPTxiU27OGOS&sparams=expire%2Cei%2Cip%2Cid%2Caitags%2Csource%2Crequiressl%2Cvprv%2Cmime%2Cns%2Cgir%2Cclen%2Cdur%2Clmt&lsparams=mh%2Cmm%2Cmn%2Cms%2Cmv%2Cmvi%2Cpl%2Cinitcwndbps&lsig=AG3C_xAwRQIgcXWsa-zXEdwHVqlmoaHnN7qN-qs0T3D-qi8BqQjd9wgCIQCgie_rJZ5s8CcGl8JAsirkw6tXSi4dglOxtlIYKbvIPQ%3D%3D&sig=AOq0QJ8wRQIhAOR1aajUS4tGRqL-BZvv-D7gZJ6yppbFgftEuGDdIs1IAiA0B26o158-o2m6MHzdF0EChVOqAg8vIz8NBLySgS6QOQ==", "width": 480, "ext": "mp4", "vcodec": "avc1.4d401e", "acodec": "none", "vbr": 159.734, "downloader_options": {"http_chunk_size": 10485760}, "container": "mp4_dash", "format": "134 - 480x360 (360p)", "protocol": "https", "http_headers": {"User-Agent": "Mozilla/5.0 (Windows NT 10.0; Win64; x64) AppleWebKit/537.36 (KHTML, like Gecko) Chrome/72.0.3592.0 Safari/537.36", "Accept-Charset": "ISO-8859-1,utf-8;q=0.7,*;q=0.7", "Accept": "text/html,application/xhtml+xml,application/xml;q=0.9,*/*;q=0.8", "Accept-Encoding": "gzip, deflate", "Accept-Language": "en-us,en;q=0.5"}}, {"asr": null, "filesize": 8889558, "format_id": "244", "format_note": "480p", "fps": 30, "height": 480, "quality": 3, "tbr": 226.837, "url": "https://rr4---sn-0opoxu-ihv6.googlevideo.com/videoplayback?expire=1670697785&ei=2X6UY7OeEI30kgbHo7z4Cw&ip=189.173.225.87&id=o-AOAj3b2OrNWhfJszppld8ApRwwiZ8ydqEkMy76gwdpEb&itag=244&aitags=133%2C134%2C135%2C136%2C137%2C160%2C242%2C243%2C244%2C247%2C248%2C278%2C394%2C395%2C396%2C397%2C398%2C399&source=youtube&requiressl=yes&mh=6I&mm=31%2C29&mn=sn-0opoxu-ihv6%2Csn-q4flrn7r&ms=au%2Crdu&mv=m&mvi=4&pl=24&initcwndbps=1000000&vprv=1&mime=video%2Fwebm&ns=NTU2HOwc2ZEoFEnMJwttG7YJ&gir=yes&clen=8889558&dur=313.513&lmt=1667584606468206&mt=1670675841&fvip=1&keepalive=yes&fexp=24001373%2C24007246&c=WEB&txp=5535434&n=8-ijwIPTxiU27OGOS&sparams=expire%2Cei%2Cip%2Cid%2Caitags%2Csource%2Crequiressl%2Cvprv%2Cmime%2Cns%2Cgir%2Cclen%2Cdur%2Clmt&lsparams=mh%2Cmm%2Cmn%2Cms%2Cmv%2Cmvi%2Cpl%2Cinitcwndbps&lsig=AG3C_xAwRQIhAPsJW_43lnh1Cv_iTqApJuFLGS63nPL7oWyVdmehBLN_AiBF26E9QYRxtKzHJHTBm38RJhLshHu4X9FJtX4PrStcxg%3D%3D&sig=AOq0QJ8wRQIhAMVC0f_2PYtTaUzRWQhhxbSe-obUAZg5GvaWUks4Z5u3AiBg-61u7ONcVoLXq1MsMfJzuLXEtpfXe03rY15yAAnYSA==", "width": 640, "ext": "webm", "vcodec": "vp9", "acodec": "none", "vbr": 226.837, "downloader_options": {"http_chunk_size": 10485760}, "container": "webm_dash", "format": "244 - 640x480 (480p)", "protocol": "https", "http_headers": {"User-Agent": "Mozilla/5.0 (Windows NT 10.0; Win64; x64) AppleWebKit/537.36 (KHTML, like Gecko) Chrome/72.0.3592.0 Safari/537.36", "Accept-Charset": "ISO-8859-1,utf-8;q=0.7,*;q=0.7", "Accept": "text/html,application/xhtml+xml,application/xml;q=0.9,*/*;q=0.8", "Accept-Encoding": "gzip, deflate", "Accept-Language": "en-us,en;q=0.5"}}, {"asr": null, "filesize": 9332266, "format_id": "135", "format_note": "480p", "fps": 30, "height": 480, "quality": 3, "tbr": 238.134, "url": "https://rr4---sn-0opoxu-ihv6.googlevideo.com/videoplayback?expire=1670697785&ei=2X6UY7OeEI30kgbHo7z4Cw&ip=189.173.225.87&id=o-AOAj3b2OrNWhfJszppld8ApRwwiZ8ydqEkMy76gwdpEb&itag=135&aitags=133%2C134%2C135%2C136%2C137%2C160%2C242%2C243%2C244%2C247%2C248%2C278%2C394%2C395%2C396%2C397%2C398%2C399&source=youtube&requiressl=yes&mh=6I&mm=31%2C29&mn=sn-0opoxu-ihv6%2Csn-q4flrn7r&ms=au%2Crdu&mv=m&mvi=4&pl=24&initcwndbps=1000000&vprv=1&mime=video%2Fmp4&ns=NTU2HOwc2ZEoFEnMJwttG7YJ&gir=yes&clen=9332266&dur=313.513&lmt=1556962785370550&mt=1670675841&fvip=1&keepalive=yes&fexp=24001373%2C24007246&c=WEB&txp=5535432&n=8-ijwIPTxiU27OGOS&sparams=expire%2Cei%2Cip%2Cid%2Caitags%2Csource%2Crequiressl%2Cvprv%2Cmime%2Cns%2Cgir%2Cclen%2Cdur%2Clmt&lsparams=mh%2Cmm%2Cmn%2Cms%2Cmv%2Cmvi%2Cpl%2Cinitcwndbps&lsig=AG3C_xAwRQIhAPJVcTLBrpUDLZ6n0syaQyFOehsEHvJy3Mi1kJAISfjoAiAB--DWJHOR9dywYBHfv5nRPicxH7wcHpCBoYc_q7dJqw%3D%3D&sig=AOq0QJ8wRQIhAP94hy9R0-1Arb2tyCiUFaN5iyRw3vaMNXmNAAUO7PSUAiAujDrUg0IhA65_ITWK05whBD_ZwQc_MBxIPuEejX2uzQ==", "width": 640, "ext": "mp4", "vcodec": "avc1.4d401e", "acodec": "none", "vbr": 238.134, "downloader_options": {"http_chunk_size": 10485760}, "container": "mp4_dash", "format": "135 - 640x480 (480p)", "protocol": "https", "http_headers": {"User-Agent": "Mozilla/5.0 (Windows NT 10.0; Win64; x64) AppleWebKit/537.36 (KHTML, like Gecko) Chrome/72.0.3592.0 Safari/537.36", "Accept-Charset": "ISO-8859-1,utf-8;q=0.7,*;q=0.7", "Accept": "text/html,application/xhtml+xml,application/xml;q=0.9,*/*;q=0.8", "Accept-Encoding": "gzip, deflate", "Accept-Language": "en-us,en;q=0.5"}}, {"asr": null, "filesize": 9517506, "format_id": "397", "format_note": "480p", "fps": 30, "height": 480, "quality": 3, "tbr": 242.86, "url": "https://rr4---sn-0opoxu-ihv6.googlevideo.com/videoplayback?expire=1670697785&ei=2X6UY7OeEI30kgbHo7z4Cw&ip=189.173.225.87&id=o-AOAj3b2OrNWhfJszppld8ApRwwiZ8ydqEkMy76gwdpEb&itag=397&aitags=133%2C134%2C135%2C136%2C137%2C160%2C242%2C243%2C244%2C247%2C248%2C278%2C394%2C395%2C396%2C397%2C398%2C399&source=youtube&requiressl=yes&mh=6I&mm=31%2C29&mn=sn-0opoxu-ihv6%2Csn-q4flrn7r&ms=au%2Crdu&mv=m&mvi=4&pl=24&initcwndbps=1000000&vprv=1&mime=video%2Fmp4&ns=NTU2HOwc2ZEoFEnMJwttG7YJ&gir=yes&clen=9517506&dur=313.513&lmt=1668717567347515&mt=1670675841&fvip=1&keepalive=yes&fexp=24001373%2C24007246&c=WEB&txp=5537434&n=8-ijwIPTxiU27OGOS&sparams=expire%2Cei%2Cip%2Cid%2Caitags%2Csource%2Crequiressl%2Cvprv%2Cmime%2Cns%2Cgir%2Cclen%2Cdur%2Clmt&lsparams=mh%2Cmm%2Cmn%2Cms%2Cmv%2Cmvi%2Cpl%2Cinitcwndbps&lsig=AG3C_xAwRQIhAPoYhwBXZTfnW_WOTukqxjjwL0YOJZoCXHbbPcdS6iD-AiAWnw-KUqnncbTslUAvUiqRyLTS85fHGn0YNS8dqC-JIQ%3D%3D&sig=AOq0QJ8wRgIhAPHgYe2cuAfC-ZMHVK0kQx_quXF_UjjbOZI5Lxlr-ZcoAiEAuMe6zk4UnTY48BCPKco4NGuRJqB8vwVCshfnuATVE9c=", "width": 640, "ext": "mp4", "vcodec": "av01.0.04M.08", "acodec": "none", "vbr": 242.86, "downloader_options": {"http_chunk_size": 10485760}, "container": "mp4_dash", "format": "397 - 640x480 (480p)", "protocol": "https", "http_headers": {"User-Agent": "Mozilla/5.0 (Windows NT 10.0; Win64; x64) AppleWebKit/537.36 (KHTML, like Gecko) Chrome/72.0.3592.0 Safari/537.36", "Accept-Charset": "ISO-8859-1,utf-8;q=0.7,*;q=0.7", "Accept": "text/html,application/xhtml+xml,application/xml;q=0.9,*/*;q=0.8", "Accept-Encoding": "gzip, deflate", "Accept-Language": "en-us,en;q=0.5"}}, {"asr": null, "filesize": 14363877, "format_id": "136", "format_note": "720p", "fps": 30, "height": 720, "quality": 4, "tbr": 366.527, "url": "https://rr4---sn-0opoxu-ihv6.googlevideo.com/videoplayback?expire=1670697785&ei=2X6UY7OeEI30kgbHo7z4Cw&ip=189.173.225.87&id=o-AOAj3b2OrNWhfJszppld8ApRwwiZ8ydqEkMy76gwdpEb&itag=136&aitags=133%2C134%2C135%2C136%2C137%2C160%2C242%2C243%2C244%2C247%2C248%2C278%2C394%2C395%2C396%2C397%2C398%2C399&source=youtube&requiressl=yes&mh=6I&mm=31%2C29&mn=sn-0opoxu-ihv6%2Csn-q4flrn7r&ms=au%2Crdu&mv=m&mvi=4&pl=24&initcwndbps=1000000&vprv=1&mime=video%2Fmp4&ns=NTU2HOwc2ZEoFEnMJwttG7YJ&gir=yes&clen=14363877&dur=313.513&lmt=1556962807816263&mt=1670675841&fvip=1&keepalive=yes&fexp=24001373%2C24007246&c=WEB&txp=5535432&n=8-ijwIPTxiU27OGOS&sparams=expire%2Cei%2Cip%2Cid%2Caitags%2Csource%2Crequiressl%2Cvprv%2Cmime%2Cns%2Cgir%2Cclen%2Cdur%2Clmt&lsparams=mh%2Cmm%2Cmn%2Cms%2Cmv%2Cmvi%2Cpl%2Cinitcwndbps&lsig=AG3C_xAwRQIgShADZ3ziuiv0DE8Kl_nuMUyfK0dL98I6KDu6_Y-P204CIQDdOfuxH0RLmdCdsrbFfdtjQbGelTU-LxWBO_DB75f14A%3D%3D&sig=AOq0QJ8wRAIgKnwxwGOtpaD-U7r-X9lCLCoj78QqHBGw4ynZxAfJObICIBF-hW32dFvlSUwaoWIejGs3QPoy77NC_rIkbNcxFOGX", "width": 960, "ext": "mp4", "vcodec": "avc1.4d401f", "acodec": "none", "vbr": 366.527, "downloader_options": {"http_chunk_size": 10485760}, "container": "mp4_dash", "format": "136 - 960x720 (720p)", "protocol": "https", "http_headers": {"User-Agent": "Mozilla/5.0 (Windows NT 10.0; Win64; x64) AppleWebKit/537.36 (KHTML, like Gecko) Chrome/72.0.3592.0 Safari/537.36", "Accept-Charset": "ISO-8859-1,utf-8;q=0.7,*;q=0.7", "Accept": "text/html,application/xhtml+xml,application/xml;q=0.9,*/*;q=0.8", "Accept-Encoding": "gzip, deflate", "Accept-Language": "en-us,en;q=0.5"}}, {"asr": null, "filesize": 14606418, "format_id": "247", "format_note": "720p", "fps": 30, "height": 720, "quality": 4, "tbr": 372.716, "url": "https://rr4---sn-0opoxu-ihv6.googlevideo.com/videoplayback?expire=1670697785&ei=2X6UY7OeEI30kgbHo7z4Cw&ip=189.173.225.87&id=o-AOAj3b2OrNWhfJszppld8ApRwwiZ8ydqEkMy76gwdpEb&itag=247&aitags=133%2C134%2C135%2C136%2C137%2C160%2C242%2C243%2C244%2C247%2C248%2C278%2C394%2C395%2C396%2C397%2C398%2C399&source=youtube&requiressl=yes&mh=6I&mm=31%2C29&mn=sn-0opoxu-ihv6%2Csn-q4flrn7r&ms=au%2Crdu&mv=m&mvi=4&pl=24&initcwndbps=1000000&vprv=1&mime=video%2Fwebm&ns=NTU2HOwc2ZEoFEnMJwttG7YJ&gir=yes&clen=14606418&dur=313.513&lmt=1667584632414767&mt=1670675841&fvip=1&keepalive=yes&fexp=24001373%2C24007246&c=WEB&txp=5535434&n=8-ijwIPTxiU27OGOS&sparams=expire%2Cei%2Cip%2Cid%2Caitags%2Csource%2Crequiressl%2Cvprv%2Cmime%2Cns%2Cgir%2Cclen%2Cdur%2Clmt&lsparams=mh%2Cmm%2Cmn%2Cms%2Cmv%2Cmvi%2Cpl%2Cinitcwndbps&lsig=AG3C_xAwRAIgMJc1VSBhvb1tyHrwNTSN2I0Ky71YZAXZla5IHxdkVl8CID-CudQKPXhynzmauaGue19iHbsDn1PqQptL5-EqWsC8&sig=AOq0QJ8wRAIgXhuP0Wx1tH2_LRUYS8HmnqY7A8EWn3SXR_Ma34I-IiMCIFsagO8aySaCuorL9CotGCiXDlCnBne07JSXjWlB4qmr", "width": 960, "ext": "webm", "vcodec": "vp9", "acodec": "none", "vbr": 372.716, "downloader_options": {"http_chunk_size": 10485760}, "container": "webm_dash", "format": "247 - 960x720 (720p)", "protocol": "https", "http_headers": {"User-Agent": "Mozilla/5.0 (Windows NT 10.0; Win64; x64) AppleWebKit/537.36 (KHTML, like Gecko) Chrome/72.0.3592.0 Safari/537.36", "Accept-Charset": "ISO-8859-1,utf-8;q=0.7,*;q=0.7", "Accept": "text/html,application/xhtml+xml,application/xml;q=0.9,*/*;q=0.8", "Accept-Encoding": "gzip, deflate", "Accept-Language": "en-us,en;q=0.5"}}, {"asr": null, "filesize": 16684734, "format_id": "398", "format_note": "720p", "fps": 30, "height": 720, "quality": 4, "tbr": 425.749, "url": "https://rr4---sn-0opoxu-ihv6.googlevideo.com/videoplayback?expire=1670697785&ei=2X6UY7OeEI30kgbHo7z4Cw&ip=189.173.225.87&id=o-AOAj3b2OrNWhfJszppld8ApRwwiZ8ydqEkMy76gwdpEb&itag=398&aitags=133%2C134%2C135%2C136%2C137%2C160%2C242%2C243%2C244%2C247%2C248%2C278%2C394%2C395%2C396%2C397%2C398%2C399&source=youtube&requiressl=yes&mh=6I&mm=31%2C29&mn=sn-0opoxu-ihv6%2Csn-q4flrn7r&ms=au%2Crdu&mv=m&mvi=4&pl=24&initcwndbps=1000000&vprv=1&mime=video%2Fmp4&ns=NTU2HOwc2ZEoFEnMJwttG7YJ&gir=yes&clen=16684734&dur=313.513&lmt=1668716043437047&mt=1670675841&fvip=1&keepalive=yes&fexp=24001373%2C24007246&c=WEB&txp=5537434&n=8-ijwIPTxiU27OGOS&sparams=expire%2Cei%2Cip%2Cid%2Caitags%2Csource%2Crequiressl%2Cvprv%2Cmime%2Cns%2Cgir%2Cclen%2Cdur%2Clmt&lsparams=mh%2Cmm%2Cmn%2Cms%2Cmv%2Cmvi%2Cpl%2Cinitcwndbps&lsig=AG3C_xAwRQIgdPlNN-qOuVxg1Bi5A3BWFPWQE720KLYdMm43alWXP9ACIQCALKcOKuO_0GYuLwLW6-Hbo2k0i94uyJsvasmJXn1PBg%3D%3D&sig=AOq0QJ8wRgIhAKupN0fRbRoHpOkeJcJ-a021ZcOFv9XUNOYmHPQwsM5mAiEA4ujFdKREn6QNmISM51fCy66eaoesct9_1_RxFTK2uB4=", "width": 960, "ext": "mp4", "vcodec": "av01.0.05M.08", "acodec": "none", "vbr": 425.749, "downloader_options": {"http_chunk_size": 10485760}, "container": "mp4_dash", "format": "398 - 960x720 (720p)", "protocol": "https", "http_headers": {"User-Agent": "Mozilla/5.0 (Windows NT 10.0; Win64; x64) AppleWebKit/537.36 (KHTML, like Gecko) Chrome/72.0.3592.0 Safari/537.36", "Accept-Charset": "ISO-8859-1,utf-8;q=0.7,*;q=0.7", "Accept": "text/html,application/xhtml+xml,application/xml;q=0.9,*/*;q=0.8", "Accept-Encoding": "gzip, deflate", "Accept-Language": "en-us,en;q=0.5"}}, {"asr": null, "filesize": 29427612, "format_id": "399", "format_note": "1080p", "fps": 30, "height": 1080, "quality": 5, "tbr": 750.912, "url": "https://rr4---sn-0opoxu-ihv6.googlevideo.com/videoplayback?expire=1670697785&ei=2X6UY7OeEI30kgbHo7z4Cw&ip=189.173.225.87&id=o-AOAj3b2OrNWhfJszppld8ApRwwiZ8ydqEkMy76gwdpEb&itag=399&aitags=133%2C134%2C135%2C136%2C137%2C160%2C242%2C243%2C244%2C247%2C248%2C278%2C394%2C395%2C396%2C397%2C398%2C399&source=youtube&requiressl=yes&mh=6I&mm=31%2C29&mn=sn-0opoxu-ihv6%2Csn-q4flrn7r&ms=au%2Crdu&mv=m&mvi=4&pl=24&initcwndbps=1000000&vprv=1&mime=video%2Fmp4&ns=NTU2HOwc2ZEoFEnMJwttG7YJ&gir=yes&clen=29427612&dur=313.513&lmt=1668718653433771&mt=1670675841&fvip=1&keepalive=yes&fexp=24001373%2C24007246&c=WEB&txp=5537434&n=8-ijwIPTxiU27OGOS&sparams=expire%2Cei%2Cip%2Cid%2Caitags%2Csource%2Crequiressl%2Cvprv%2Cmime%2Cns%2Cgir%2Cclen%2Cdur%2Clmt&lsparams=mh%2Cmm%2Cmn%2Cms%2Cmv%2Cmvi%2Cpl%2Cinitcwndbps&lsig=AG3C_xAwRQIhALQlzadTCgbM1wUbx7E2ItyGwokZ3ev5rxRpAXYbS6ztAiAWLXejgq_rTZF4ixsADvfDKLxCU_7OF1T1rmGQfaVKrA%3D%3D&sig=AOq0QJ8wRQIhAOgTRmzeGeDGjhbBXF7uBVI-g_VGs_p_2VcJJAZwrECpAiByswUCa5YhosYL9Q61iIHipLMi7dyUGv2XWs8BYwkZeg==", "width": 1440, "ext": "mp4", "vcodec": "av01.0.08M.08", "acodec": "none", "vbr": 750.912, "downloader_options": {"http_chunk_size": 10485760}, "container": "mp4_dash", "format": "399 - 1440x1080 (1080p)", "protocol": "https", "http_headers": {"User-Agent": "Mozilla/5.0 (Windows NT 10.0; Win64; x64) AppleWebKit/537.36 (KHTML, like Gecko) Chrome/72.0.3592.0 Safari/537.36", "Accept-Charset": "ISO-8859-1,utf-8;q=0.7,*;q=0.7", "Accept": "text/html,application/xhtml+xml,application/xml;q=0.9,*/*;q=0.8", "Accept-Encoding": "gzip, deflate", "Accept-Language": "en-us,en;q=0.5"}}, {"asr": null, "filesize": 40378093, "format_id": "248", "format_note": "1080p", "fps": 30, "height": 1080, "quality": 5, "tbr": 1030.339, "url": "https://rr4---sn-0opoxu-ihv6.googlevideo.com/videoplayback?expire=1670697785&ei=2X6UY7OeEI30kgbHo7z4Cw&ip=189.173.225.87&id=o-AOAj3b2OrNWhfJszppld8ApRwwiZ8ydqEkMy76gwdpEb&itag=248&aitags=133%2C134%2C135%2C136%2C137%2C160%2C242%2C243%2C244%2C247%2C248%2C278%2C394%2C395%2C396%2C397%2C398%2C399&source=youtube&requiressl=yes&mh=6I&mm=31%2C29&mn=sn-0opoxu-ihv6%2Csn-q4flrn7r&ms=au%2Crdu&mv=m&mvi=4&pl=24&initcwndbps=1000000&vprv=1&mime=video%2Fwebm&ns=NTU2HOwc2ZEoFEnMJwttG7YJ&gir=yes&clen=40378093&dur=313.513&lmt=1667584653944094&mt=1670675841&fvip=1&keepalive=yes&fexp=24001373%2C24007246&c=WEB&txp=5535434&n=8-ijwIPTxiU27OGOS&sparams=expire%2Cei%2Cip%2Cid%2Caitags%2Csource%2Crequiressl%2Cvprv%2Cmime%2Cns%2Cgir%2Cclen%2Cdur%2Clmt&lsparams=mh%2Cmm%2Cmn%2Cms%2Cmv%2Cmvi%2Cpl%2Cinitcwndbps&lsig=AG3C_xAwRgIhAKoRlgxx5RdgN39v2fX9z8C1UFwrn_r2tPO7ilGfBzr6AiEAyHh6_iEzOsQ8-Q_J_9uz1iQFmeDVWD1sWnjRGiMbOWY%3D&sig=AOq0QJ8wRAIgfdf-0SE_6NSAqBgVR2a4xIwcCmD_jc3uoyiO63Y1mzECIDHWOZd4C65FUF844IJiS88zy04osxKYCu_AtJtRJNJI", "width": 1440, "ext": "webm", "vcodec": "vp9", "acodec": "none", "vbr": 1030.339, "downloader_options": {"http_chunk_size": 10485760}, "container": "webm_dash", "format": "248 - 1440x1080 (1080p)", "protocol": "https", "http_headers": {"User-Agent": "Mozilla/5.0 (Windows NT 10.0; Win64; x64) AppleWebKit/537.36 (KHTML, like Gecko) Chrome/72.0.3592.0 Safari/537.36", "Accept-Charset": "ISO-8859-1,utf-8;q=0.7,*;q=0.7", "Accept": "text/html,application/xhtml+xml,application/xml;q=0.9,*/*;q=0.8", "Accept-Encoding": "gzip, deflate", "Accept-Language": "en-us,en;q=0.5"}}, {"asr": null, "filesize": 42548137, "format_id": "137", "format_note": "1080p", "fps": 30, "height": 1080, "quality": 5, "tbr": 1085.712, "url": "https://rr4---sn-0opoxu-ihv6.googlevideo.com/videoplayback?expire=1670697785&ei=2X6UY7OeEI30kgbHo7z4Cw&ip=189.173.225.87&id=o-AOAj3b2OrNWhfJszppld8ApRwwiZ8ydqEkMy76gwdpEb&itag=137&aitags=133%2C134%2C135%2C136%2C137%2C160%2C242%2C243%2C244%2C247%2C248%2C278%2C394%2C395%2C396%2C397%2C398%2C399&source=youtube&requiressl=yes&mh=6I&mm=31%2C29&mn=sn-0opoxu-ihv6%2Csn-q4flrn7r&ms=au%2Crdu&mv=m&mvi=4&pl=24&initcwndbps=1000000&vprv=1&mime=video%2Fmp4&ns=NTU2HOwc2ZEoFEnMJwttG7YJ&gir=yes&clen=42548137&dur=313.513&lmt=1556962859738952&mt=1670675841&fvip=1&keepalive=yes&fexp=24001373%2C24007246&c=WEB&txp=5535432&n=8-ijwIPTxiU27OGOS&sparams=expire%2Cei%2Cip%2Cid%2Caitags%2Csource%2Crequiressl%2Cvprv%2Cmime%2Cns%2Cgir%2Cclen%2Cdur%2Clmt&lsparams=mh%2Cmm%2Cmn%2Cms%2Cmv%2Cmvi%2Cpl%2Cinitcwndbps&lsig=AG3C_xAwRAIgOGDpcUm2JK22wdZCVYB-qHwToldFYrdWXYSM5-avggMCICVk8-1YuCT66Kwm97o3CU5cN3PHLD74QI3dO8EmTPDT&sig=AOq0QJ8wRQIgeoyLcxfytNOJ0Gr65kJEqqDmYcq5CATN-y9ELtYESCUCIQDydWU6Wf-brOrIMU1oC5nBQgprStsqOjkG09cdHrI4wg==", "width": 1440, "ext": "mp4", "vcodec": "avc1.640028", "acodec": "none", "vbr": 1085.712, "downloader_options": {"http_chunk_size": 10485760}, "container": "mp4_dash", "format": "137 - 1440x1080 (1080p)", "protocol": "https", "http_headers": {"User-Agent": "Mozilla/5.0 (Windows NT 10.0; Win64; x64) AppleWebKit/537.36 (KHTML, like Gecko) Chrome/72.0.3592.0 Safari/537.36", "Accept-Charset": "ISO-8859-1,utf-8;q=0.7,*;q=0.7", "Accept": "text/html,application/xhtml+xml,application/xml;q=0.9,*/*;q=0.8", "Accept-Encoding": "gzip, deflate", "Accept-Language": "en-us,en;q=0.5"}}, {"asr": 44100, "filesize": null, "format_id": "18", "format_note": "360p", "fps": 30, "height": 360, "quality": 2, "tbr": 288.651, "url": "https://rr4---sn-0opoxu-ihv6.googlevideo.com/videoplayback?expire=1670697785&ei=2X6UY7OeEI30kgbHo7z4Cw&ip=189.173.225.87&id=o-AOAj3b2OrNWhfJszppld8ApRwwiZ8ydqEkMy76gwdpEb&itag=18&source=youtube&requiressl=yes&mh=6I&mm=31%2C29&mn=sn-0opoxu-ihv6%2Csn-q4flrn7r&ms=au%2Crdu&mv=m&mvi=4&pl=24&initcwndbps=1000000&vprv=1&mime=video%2Fmp4&ns=0ujcg7AYGt5UBWSqIhyhTYEJ&cnr=14&ratebypass=yes&dur=313.562&lmt=1664578568244259&mt=1670675841&fvip=1&fexp=24001373%2C24007246&c=WEB&txp=5538434&n=wJ8qrHKZ_jlhGOKQa&sparams=expire%2Cei%2Cip%2Cid%2Citag%2Csource%2Crequiressl%2Cvprv%2Cmime%2Cns%2Ccnr%2Cratebypass%2Cdur%2Clmt&lsparams=mh%2Cmm%2Cmn%2Cms%2Cmv%2Cmvi%2Cpl%2Cinitcwndbps&lsig=AG3C_xAwRgIhALdt6o_kmOEWQCRReski89gv3eNMYC8sZ-8tRZM2XQoFAiEA6nc9ISRYZd47P11kOAiuyozxFrFSx8Hk2W20dbC7Yfo%3D&sig=AOq0QJ8wRgIhALoUL1SE0kGNPW3yVzoCXEG3_SbAtXMtrF9z52CaVpsjAiEAjK2X2-6k--ZJYIXcIHBGXIyC96xec3nDoaqZUfmPLNE=", "width": 480, "ext": "mp4", "vcodec": "avc1.42001E", "acodec": "mp4a.40.2", "format": "18 - 480x360 (360p)", "protocol": "https", "http_headers": {"User-Agent": "Mozilla/5.0 (Windows NT 10.0; Win64; x64) AppleWebKit/537.36 (KHTML, like Gecko) Chrome/72.0.3592.0 Safari/537.36", "Accept-Charset": "ISO-8859-1,utf-8;q=0.7,*;q=0.7", "Accept": "text/html,application/xhtml+xml,application/xml;q=0.9,*/*;q=0.8", "Accept-Encoding": "gzip, deflate", "Accept-Language": "en-us,en;q=0.5"}}], "thumbnails": [{"height": 94, "url": "https://i.ytimg.com/vi/IZBlqcbpmxY/hqdefault.jpg?sqp=-oaymwEbCKgBEF5IVfKriqkDDggBFQAAiEIYAXABwAEG&rs=AOn4CLCY9xllhy1VusIOMMoQmDLvnhnU_w", "width": 168, "resolution": "168x94", "id": "0"}, {"height": 110, "url": "https://i.ytimg.com/vi/IZBlqcbpmxY/hqdefault.jpg?sqp=-oaymwEbCMQBEG5IVfKriqkDDggBFQAAiEIYAXABwAEG&rs=AOn4CLC-B1yJVlHEJBKgjpErYgQ_xnWhTQ", "width": 196, "resolution": "196x110", "id": "1"}, {"height": 138, "url": "https://i.ytimg.com/vi/IZBlqcbpmxY/hqdefault.jpg?sqp=-oaymwEcCPYBEIoBSFXyq4qpAw4IARUAAIhCGAFwAcABBg==&rs=AOn4CLCoktNJ9iJiDs1L9Wqu3R1vCj1i8Q", "width": 246, "resolution": "246x138", "id": "2"}, {"height": 188, "url": "https://i.ytimg.com/vi/IZBlqcbpmxY/hqdefault.jpg?sqp=-oaymwEcCNACELwBSFXyq4qpAw4IARUAAIhCGAFwAcABBg==&rs=AOn4CLBwBTNOGT78dbz07pwk-uNuQH7QRA", "width": 336, "resolution": "336x188", "id": "3"}, {"height": 1080, "url": "https://i.ytimg.com/vi/IZBlqcbpmxY/maxresdefault.jpg", "width": 1920, "resolution": "1920x1080", "id": "4"}], "description": "Jimi Hendrix performing Voodoo Child (Slight Return). From the album Electric Ladyland. \u00a9 1968 Track Records\n\nThe Greatest Hits of Jimi Hendrix Playlist: https://www.youtube.com/watch?v=TLV4_xaYynY&list=PL-foX1srIqO83-uK9HiBcsHhlc2XXAFbn\n\n\"Voodoo Child (Slight Return)\" on the Electric Ladyland album. The third and final album by the Jimi Hendrix Experience. The song is known for its wah-wah-heavy guitar work. It is #101 on Rolling Stone's list of 500 greatest songs of all time.\n\nMore from Jimi Hendrix (The Jimi Hendrix Experience):\nhttps://music.youtube.com/channel/UC5NwXf8hOgZgInaYiOCZmUg\nhttps://open.spotify.com/artist/776Uo845nYHJpNaStv1Ds4\nhttps://www.deezer.com/us/artist/849\nhttps://twitter.com/JimiHendrix\nhttps://www.jimihendrix.com\nhttps://jimihendrix.social\nhttps://www.authentichendrix.com\n\n#JimiHendrix #VoodooChild #SlightReturn", "upload_date": "20140521", "uploader": "Echelon Recordings", "uploader_id": "josepht007", "uploader_url": "http://www.youtube.com/user/josepht007", "channel_id": "UCdlWpO4WB7BFF4ZgsgRJxvg", "channel_url": "https://www.youtube.com/channel/UCdlWpO4WB7BFF4ZgsgRJxvg", "duration": 314, "view_count": 40521081, "average_rating": null, "age_limit": 0, "webpage_url": "https://www.youtube.com/watch?v=IZBlqcbpmxY", "categories": ["Music"], "tags": ["jimi hendrix", "voodoo child", "voodoo child slight return", "jimi hendrix voodoo child", "voodoo chile", "hendrix", "jimi hendrix voodoo chile", "voodoo child (slight return)", "jimi hendrix voodoo child slight return tradu\u00e7\u00e3o", "jimi hendrix voodoo child slight return legendado", "voodoo chile slight return jimi hendrix", "jimi hendrix live", "voodoo child (slight return) (composition)", "jimi hendrix voodoo", "the jimi hendrix experience", "jimi hendrix video"], "is_live": null, "channel": "Echelon Recordings", "extractor": "youtube", "webpage_url_basename": "watch", "extractor_key": "Youtube", "playlist": null, "playlist_index": null, "thumbnail": "https://i.ytimg.com/vi/IZBlqcbpmxY/maxresdefault.jpg", "display_id": "IZBlqcbpmxY", "asr": 44100, "filesize": null, "format_id": "18", "format_note": "360p", "fps": 30, "height": 360, "quality": 2, "tbr": 288.651, "url": "https://rr4---sn-0opoxu-ihv6.googlevideo.com/videoplayback?expire=1670697785&ei=2X6UY7OeEI30kgbHo7z4Cw&ip=189.173.225.87&id=o-AOAj3b2OrNWhfJszppld8ApRwwiZ8ydqEkMy76gwdpEb&itag=18&source=youtube&requiressl=yes&mh=6I&mm=31%2C29&mn=sn-0opoxu-ihv6%2Csn-q4flrn7r&ms=au%2Crdu&mv=m&mvi=4&pl=24&initcwndbps=1000000&vprv=1&mime=video%2Fmp4&ns=0ujcg7AYGt5UBWSqIhyhTYEJ&cnr=14&ratebypass=yes&dur=313.562&lmt=1664578568244259&mt=1670675841&fvip=1&fexp=24001373%2C24007246&c=WEB&txp=5538434&n=wJ8qrHKZ_jlhGOKQa&sparams=expire%2Cei%2Cip%2Cid%2Citag%2Csource%2Crequiressl%2Cvprv%2Cmime%2Cns%2Ccnr%2Cratebypass%2Cdur%2Clmt&lsparams=mh%2Cmm%2Cmn%2Cms%2Cmv%2Cmvi%2Cpl%2Cinitcwndbps&lsig=AG3C_xAwRgIhALdt6o_kmOEWQCRReski89gv3eNMYC8sZ-8tRZM2XQoFAiEA6nc9ISRYZd47P11kOAiuyozxFrFSx8Hk2W20dbC7Yfo%3D&sig=AOq0QJ8wRgIhALoUL1SE0kGNPW3yVzoCXEG3_SbAtXMtrF9z52CaVpsjAiEAjK2X2-6k--ZJYIXcIHBGXIyC96xec3nDoaqZUfmPLNE=", "width": 480, "ext": "mp4", "vcodec": "avc1.42001E", "acodec": "mp4a.40.2", "format": "18 - 480x360 (360p)", "protocol": "https", "http_headers": {"User-Agent": "Mozilla/5.0 (Windows NT 10.0; Win64; x64) AppleWebKit/537.36 (KHTML, like Gecko) Chrome/72.0.3592.0 Safari/537.36", "Accept-Charset": "ISO-8859-1,utf-8;q=0.7,*;q=0.7", "Accept": "text/html,application/xhtml+xml,application/xml;q=0.9,*/*;q=0.8", "Accept-Encoding": "gzip, deflate", "Accept-Language": "en-us,en;q=0.5"}, "fulltitle": "Jimi Hendrix - Voodoo Child (Slight Return)", "_filename": "Jimi Hendrix - Voodoo Child (Slight Return)-IZBlqcbpmxY.mp4"}